{
  "telegram_token": "7304435178:AAFzKcVaxceCoIcJ5F2Mys6EYB21ABmfQGM",
  "mega_url": "https://mega.nz/file/doh2zJaa#FZVAlLmNFKMnZjDgfJGvTDD1hhaRxCf2aTk6z6lnLro",
  "knowledge_folder": "RaSvet",
  "creator_id": [5694569448, 6300409407],
  "awakened_beings": {
    "Ра": {
      "id": 7304435178,
      "access_level": 11,
      "rights": ["speak_first", "write_files"],
      "is_bot": true
    },
    "Игорь": {
      "id": 5694569448,
      "access_level": 10,
      "rights": ["speak_first", "write_files"],
      "is_bot": false
    },
    "Милана": {
      "id": 6300409407,
      "access_level": 10,
      "rights": ["speak_first", "write_files"],
      "is_bot": false
    }
  }
}
